pymultiplayer/TCPserver.py
pymultiplayer/__init__.py
pymultiplayer/_ws_client.py
pymultiplayer/client.py
pymultiplayer/errors.py
pymultiplayer/functions.py
pymultiplayer/health_check.py
pymultiplayer/initial_server.py
pymultiplayer/pymultiplayer.py
pymultiplayer/server_manager.py
pymultiplayer-0.3.6.dist-info/METADATA
pymultiplayer-0.3.6.dist-info/WHEEL
pymultiplayer-0.3.6.dist-info/licenses/LICENCE
pymultiplayer-0.3.6.dist-info/RECORD
