Metadata-Version: 2.4
Name: pymultiplayer
Version: 0.3.6
Summary: A package for adding multiplayer functionality to python games.
Project-URL: Homepage, https://github.com/iamdeedz/pymultiplayer
Project-URL: Bug Tracker, https://github.com/iamdeedz/pymultiplayer/issues
Author: iamdeedz
License: MIT License
License-File: LICENCE
Keywords: coop,cooperative,game,multiplayer,pygame
Requires-Python: >=3
Requires-Dist: websockets
